AUTHORS
LICENSE
MANIFEST.in
README.rst
setup.py
docs/Makefile
docs/changes.rst
docs/conf.py
docs/contributing.rst
docs/credits.rst
docs/index.rst
docs/installation.rst
docs/make.bat
docs/_ext/__init__.py
docs/_ext/django_models.py
docs/api/index.rst
docs/api/views.rst
dproxy/__init__.py
dproxy/admin.py
dproxy/models.py
dproxy/views.py
dproxy.egg-info/PKG-INFO
dproxy.egg-info/SOURCES.txt
dproxy.egg-info/dependency_links.txt
dproxy.egg-info/requires.txt
dproxy.egg-info/top_level.txt